Metadata-Version: 1.0
Name: sysstat
Version: 0.1
Summary: Script to collect PC usage statistics
Home-page: UNKNOWN
Author: Ilya_Yaruk
Author-email: ilya_yaruk@epam.com
License: MIT
Platform: UNKNOWN
